MANIFEST.in
README.rst
setup.py
zcbot_cache_sdk.egg-info/PKG-INFO
zcbot_cache_sdk.egg-info/SOURCES.txt
zcbot_cache_sdk.egg-info/dependency_links.txt
zcbot_cache_sdk.egg-info/requires.txt
zcbot_cache_sdk.egg-info/top_level.txt
zcbot_cacke_sdk/__init__.py
zcbot_cacke_sdk/constant.py
zcbot_cacke_sdk/model.py
zcbot_cacke_sdk/sku_cache.py
zcbot_cacke_sdk/utils.py