Metadata-Version: 2.1
Name: zcbot-cache-sdk
Version: 0.0.22
Summary: zcbot cache for zsodata
Home-page: http://www.zsodata.com
Author: zsodata
Author-email: team@zso.io
License: BSD License
Platform: all
Requires-Python: >=3.7
